ro_fsm/__init__.py
ro_fsm/fsm.py
ro_fsm/yaml_loader.py
ro_fsm-0.7.0.dist-info/WHEEL
ro_fsm-0.7.0.dist-info/entry_points.txt
ro_fsm-0.7.0.dist-info/METADATA
ro_fsm-0.7.0.dist-info/RECORD
