Metadata-Version: 2.3
Name: ro-fsm
Version: 0.7.0
Summary: lightweight, context-driven finite state machine (FSM) library.
Author: Rodrigo Francisco
Author-email: Rodrigo Francisco <rodrigofrancisco@tecnico.ulisboa.pt>
License: MIT License
Requires-Dist: pyyaml>=6.0,<7.0
Requires-Python: >=3.12
